GlassJoke/__init__.py
GlassJoke/main.py
GlassJoke/types/__init__.py
GlassJoke/types/glass.py
GlassJoke/types/intern.py
src/__init__.py
src/main.py
src/types/__init__.py
src/types/glass.py
src/types/intern.py
glass_joke-1.0.1.dist-info/METADATA
glass_joke-1.0.1.dist-info/WHEEL
glass_joke-1.0.1.dist-info/top_level.txt
glass_joke-1.0.1.dist-info/RECORD
