Metadata-Version: 2.1
Name: glass-joke
Version: 1.0.1
Summary: The python way
Author: TrashPoster
